econopy/__init__.py
econopy/calculos/__init__.py
econopy/prestamos/__init__.py
econopy/rentas/__init__.py
econopy/rentas/actualizacion.py
econopy/rentas/capitalizacion.py
econopy/tipos/__init__.py
econopy-0.0.3.dist-info/METADATA
econopy-0.0.3.dist-info/RECORD
econopy-0.0.3.dist-info/WHEEL
econopy-0.0.3.dist-info/top_level.txt
tests/unit/__init__.py
tests/unit/test_import.py
