Metadata-Version: 2.1
Name: econopy
Version: 0.0.3
Summary: Simple economic utilities
Home-page: https://github.com/KeoH/econoPy
Author: Francisco Manzano Magaña
Author-email: keoh77@gmail.com
License: UNKNOWN
Project-URL: Bug Reports, https://github.com/KeoH/econoPy/issues
Project-URL: Source, https://github.com/KeoH/econoPy/
Keywords: economic,financial,business,accounting
Platform: UNKNOWN
Classifier: Development Status :: 1 - Planning
Classifier: Intended Audience :: Developers
Classifier: Topic :: Office/Business :: Financial :: Accounting
Classifier: License :: OSI Approved :: MIT License
Classifier: Programming Language :: Python :: 3
Classifier: Programming Language :: Python :: 3.4
Classifier: Programming Language :: Python :: 3.5
Classifier: Programming Language :: Python :: 3.6
Classifier: Programming Language :: Python :: 3.7
Provides-Extra: dev
Provides-Extra: test
Provides-Extra: dev
Requires-Dist: check-manifest; extra == 'dev'
Provides-Extra: test
Requires-Dist: coverage; extra == 'test'
